vl_jepa/__init__.py
vl_jepa/cli.py
vl_jepa/decoder.py
vl_jepa/detector.py
vl_jepa/encoder.py
vl_jepa/frame.py
vl_jepa/index.py
vl_jepa/multimodal_index.py
vl_jepa/storage.py
vl_jepa/text.py
vl_jepa/video.py
vl_jepa/audio/__init__.py
vl_jepa/audio/base.py
vl_jepa/audio/chunker.py
vl_jepa/audio/extractor.py
vl_jepa/audio/placeholder.py
vl_jepa/audio/transcriber.py
vl_jepa/encoders/__init__.py
vl_jepa/encoders/base.py
vl_jepa/encoders/dinov2.py
vl_jepa/encoders/placeholder.py
lecture_mind-0.2.0.dist-info/METADATA
lecture_mind-0.2.0.dist-info/WHEEL
lecture_mind-0.2.0.dist-info/entry_points.txt
lecture_mind-0.2.0.dist-info/RECORD
