Metadata-Version: 2.4
Name: lecture-mind
Version: 0.2.0
Summary: Event-aware lecture summarizer using V-JEPA
Project-URL: Homepage, https://github.com/matte1782/lecture-mind
Project-URL: Repository, https://github.com/matte1782/lecture-mind
Author: Matteo Panzeri
License-Expression: MIT
Keywords: embeddings,jepa,lecture,summarizer,video
Classifier: Development Status :: 3 - Alpha
Classifier: Intended Audience :: Education
Classifier: License :: OSI Approved :: MIT License
Classifier: Programming Language :: Python :: 3
Classifier: Programming Language :: Python :: 3.10
Classifier: Programming Language :: Python :: 3.11
Classifier: Programming Language :: Python :: 3.12
Classifier: Programming Language :: Python :: 3.13
Requires-Python: >=3.10
Requires-Dist: numpy>=1.24.0
Requires-Dist: opencv-python>=4.8.0
Provides-Extra: all
Requires-Dist: faiss-cpu>=1.7.4; extra == 'all'
Requires-Dist: faster-whisper>=1.0.0; extra == 'all'
Requires-Dist: gradio>=4.0.0; extra == 'all'
Requires-Dist: hypothesis>=6.80.0; extra == 'all'
Requires-Dist: mypy>=1.5.0; extra == 'all'
Requires-Dist: pytest-benchmark>=4.0.0; extra == 'all'
Requires-Dist: pytest-cov>=4.1.0; extra == 'all'
Requires-Dist: pytest>=7.4.0; extra == 'all'
Requires-Dist: ruff>=0.1.0; extra == 'all'
Requires-Dist: safetensors>=0.4.0; extra == 'all'
Requires-Dist: sentence-transformers>=2.2.0; extra == 'all'
Requires-Dist: torch>=2.0.0; extra == 'all'
Requires-Dist: transformers>=4.35.0; extra == 'all'
Provides-Extra: audio
Requires-Dist: faster-whisper>=1.0.0; extra == 'audio'
Provides-Extra: dev
Requires-Dist: hypothesis>=6.80.0; extra == 'dev'
Requires-Dist: mypy>=1.5.0; extra == 'dev'
Requires-Dist: pytest-benchmark>=4.0.0; extra == 'dev'
Requires-Dist: pytest-cov>=4.1.0; extra == 'dev'
Requires-Dist: pytest>=7.4.0; extra == 'dev'
Requires-Dist: ruff>=0.1.0; extra == 'dev'
Provides-Extra: ml
Requires-Dist: faiss-cpu>=1.7.4; extra == 'ml'
Requires-Dist: safetensors>=0.4.0; extra == 'ml'
Requires-Dist: sentence-transformers>=2.2.0; extra == 'ml'
Requires-Dist: torch>=2.0.0; extra == 'ml'
Requires-Dist: transformers>=4.35.0; extra == 'ml'
Provides-Extra: ui
Requires-Dist: gradio>=4.0.0; extra == 'ui'
